sqlalchemy_fdw/__init__.py
sqlalchemy_fdw/dialect.py
sqlalchemy_fdw/util.py
sqlalchemy_fdw-0.4.1.dist-info/entry_points.txt
sqlalchemy_fdw-0.4.1.dist-info/WHEEL
sqlalchemy_fdw-0.4.1.dist-info/METADATA
sqlalchemy_fdw-0.4.1.dist-info/RECORD
