Metadata-Version: 2.1
Name: sqlalchemy_fdw
Version: 0.4.1
Summary: PostgreSQL dialect supporting foreign data wrappers
Author: Kozea
Requires-Python: >=3.6
Requires-Dist: sqlalchemy>=1.3
Requires-Dist: psycopg2-binary
